TimesheetExcelEditor/CalendarPanel.py
TimesheetExcelEditor/CreatePanel.py
TimesheetExcelEditor/Excel.py
TimesheetExcelEditor/FormPanel.py
TimesheetExcelEditor/ListPanel.py
TimesheetExcelEditor/MyFrame.py
TimesheetExcelEditor/MyPanel.py
TimesheetExcelEditor/RangePanel.py
TimesheetExcelEditor/__init__.py
TimesheetExcelEditor/__main__.py
TimesheetExcelEditor/config.py
TimesheetExcelEditor-1.1.3.dist-info/LICENSE.txt
TimesheetExcelEditor-1.1.3.dist-info/METADATA
TimesheetExcelEditor-1.1.3.dist-info/WHEEL
TimesheetExcelEditor-1.1.3.dist-info/top_level.txt
TimesheetExcelEditor-1.1.3.dist-info/RECORD
