Metadata-Version: 2.1
Name: TimesheetExcelEditor
Version: 1.1.3
Summary: An application for modify excel timesheet
Home-page: https://github.com/alaino95/TimesheetExcelEditor
Author: Alessandro Laino
Author-email: alessandrolaino1@gmail.com
License: MIT
Classifier: License :: OSI Approved :: MIT License
Classifier: Programming Language :: Python :: 3
Classifier: Programming Language :: Python :: 3.9
License-File: LICENSE.txt
Requires-Dist: wxpython
Requires-Dist: openpyxl
Requires-Dist: icalendar
Requires-Dist: validators
Requires-Dist: python-dateutil
